{
  "openapi": "3.0.4",
  "info": {
    "title": "BlogApp",
    "version": "1.0"
  },
  "paths": {
    "/api/BlogApi": {
      "get": {
        "tags": [
          "BlogApi"
        ],
        "responses": {
          "200": {
            "description": "OK"
          }
        }
      },
      "post": {
        "tags": [
          "BlogApi"
        ],
        "requestBody": {
          "content": {
            "application/json": {
              "schema": {
                "$ref": "#/components/schemas/Blog"
              }
            },
            "text/json": {
              "schema": {
                "$ref": "#/components/schemas/Blog"
              }
            },
            "application/*+json": {
              "schema": {
                "$ref": "#/components/schemas/Blog"
              }
            }
          }
        },
        "responses": {
          "200": {
            "description": "OK"
          }
        }
      }
    },
    "/api/BlogApi/{id}": {
      "get": {
        "tags": [
          "BlogApi"
        ],
        "parameters": [
          {
            "name": "id",
            "in": "path",
            "required": true,
            "schema": {
              "type": "integer",
              "format": "int32"
            }
          }
        ],
        "responses": {
          "200": {
            "description": "OK"
          }
        }
      },
      "put": {
        "tags": [
          "BlogApi"
        ],
        "parameters": [
          {
            "name": "id",
            "in": "path",
            "required": true,
            "schema": {
              "type": "integer",
              "format": "int32"
            }
          }
        ],
        "requestBody": {
          "content": {
            "application/json": {
              "schema": {
                "$ref": "#/components/schemas/Blog"
              }
            },
            "text/json": {
              "schema": {
                "$ref": "#/components/schemas/Blog"
              }
            },
            "application/*+json": {
              "schema": {
                "$ref": "#/components/schemas/Blog"
              }
            }
          }
        },
        "responses": {
          "200": {
            "description": "OK"
          }
        }
      },
      "delete": {
        "tags": [
          "BlogApi"
        ],
        "parameters": [
          {
            "name": "id",
            "in": "path",
            "required": true,
            "schema": {
              "type": "integer",
              "format": "int32"
            }
          }
        ],
        "responses": {
          "200": {
            "description": "OK"
          }
        }
      }
    },
    "/api/CategoryApi": {
      "get": {
        "tags": [
          "CategoryApi"
        ],
        "responses": {
          "200": {
            "description": "OK"
          }
        }
      },
      "post": {
        "tags": [
          "CategoryApi"
        ],
        "requestBody": {
          "content": {
            "application/json": {
              "schema": {
                "$ref": "#/components/schemas/Category"
              }
            },
            "text/json": {
              "schema": {
                "$ref": "#/components/schemas/Category"
              }
            },
            "application/*+json": {
              "schema": {
                "$ref": "#/components/schemas/Category"
              }
            }
          }
        },
        "responses": {
          "200": {
            "description": "OK"
          }
        }
      }
    },
    "/api/CategoryApi/{id}": {
      "get": {
        "tags": [
          "CategoryApi"
        ],
        "parameters": [
          {
            "name": "id",
            "in": "path",
            "required": true,
            "schema": {
              "type": "integer",
              "format": "int32"
            }
          }
        ],
        "responses": {
          "200": {
            "description": "OK"
          }
        }
      }
    },
    "/api/CommentApi": {
      "get": {
        "tags": [
          "CommentApi"
        ],
        "responses": {
          "200": {
            "description": "OK"
          }
        }
      },
      "post": {
        "tags": [
          "CommentApi"
        ],
        "requestBody": {
          "content": {
            "application/json": {
              "schema": {
                "$ref": "#/components/schemas/Comment"
              }
            },
            "text/json": {
              "schema": {
                "$ref": "#/components/schemas/Comment"
              }
            },
            "application/*+json": {
              "schema": {
                "$ref": "#/components/schemas/Comment"
              }
            }
          }
        },
        "responses": {
          "200": {
            "description": "OK"
          }
        }
      }
    },
    "/api/CommentApi/{id}": {
      "get": {
        "tags": [
          "CommentApi"
        ],
        "parameters": [
          {
            "name": "id",
            "in": "path",
            "required": true,
            "schema": {
              "type": "integer",
              "format": "int32"
            }
          }
        ],
        "responses": {
          "200": {
            "description": "OK"
          }
        }
      },
      "delete": {
        "tags": [
          "CommentApi"
        ],
        "parameters": [
          {
            "name": "id",
            "in": "path",
            "required": true,
            "schema": {
              "type": "integer",
              "format": "int32"
            }
          }
        ],
        "responses": {
          "200": {
            "description": "OK"
          }
        }
      }
    },
    "/api/UserApi": {
      "get": {
        "tags": [
          "UserApi"
        ],
        "responses": {
          "200": {
            "description": "OK"
          }
        }
      },
      "post": {
        "tags": [
          "UserApi"
        ],
        "requestBody": {
          "content": {
            "application/json": {
              "schema": {
                "$ref": "#/components/schemas/User"
              }
            },
            "text/json": {
              "schema": {
                "$ref": "#/components/schemas/User"
              }
            },
            "application/*+json": {
              "schema": {
                "$ref": "#/components/schemas/User"
              }
            }
          }
        },
        "responses": {
          "200": {
            "description": "OK"
          }
        }
      }
    },
    "/api/UserApi/{id}": {
      "get": {
        "tags": [
          "UserApi"
        ],
        "parameters": [
          {
            "name": "id",
            "in": "path",
            "required": true,
            "schema": {
              "type": "integer",
              "format": "int32"
            }
          }
        ],
        "responses": {
          "200": {
            "description": "OK"
          }
        }
      },
      "delete": {
        "tags": [
          "UserApi"
        ],
        "parameters": [
          {
            "name": "id",
            "in": "path",
            "required": true,
            "schema": {
              "type": "integer",
              "format": "int32"
            }
          }
        ],
        "responses": {
          "200": {
            "description": "OK"
          }
        }
      }
    }
  },
  "components": {
    "schemas": {
      "Blog": {
        "required": [
          "categoryId",
          "content",
          "title",
          "url",
          "userId"
        ],
        "type": "object",
        "properties": {
          "blogId": {
            "type": "integer",
            "format": "int32"
          },
          "title": {
            "maxLength": 200,
            "minLength": 5,
            "type": "string"
          },
          "content": {
            "minLength": 10,
            "type": "string"
          },
          "description": {
            "maxLength": 500,
            "minLength": 0,
            "type": "string",
            "nullable": true
          },
          "createdDate": {
            "type": "string",
            "format": "date-time"
          },
          "updatedDate": {
            "type": "string",
            "format": "date-time",
            "nullable": true
          },
          "image": {
            "type": "string",
            "nullable": true
          },
          "url": {
            "maxLength": 200,
            "minLength": 0,
            "pattern": "^[a-zA-Z0-9-_]+$",
            "type": "string"
          },
          "isActive": {
            "type": "boolean"
          },
          "userId": {
            "type": "integer",
            "format": "int32"
          },
          "user": {
            "$ref": "#/components/schemas/User"
          },
          "comments": {
            "type": "array",
            "items": {
              "$ref": "#/components/schemas/Comment"
            },
            "nullable": true
          },
          "categoryId": {
            "type": "integer",
            "format": "int32"
          },
          "category": {
            "$ref": "#/components/schemas/Category"
          }
        },
        "additionalProperties": false
      },
      "Category": {
        "required": [
          "categoryName",
          "url"
        ],
        "type": "object",
        "properties": {
          "categoryId": {
            "type": "integer",
            "format": "int32"
          },
          "categoryName": {
            "maxLength": 100,
            "minLength": 2,
            "type": "string"
          },
          "description": {
            "maxLength": 500,
            "minLength": 0,
            "type": "string",
            "nullable": true
          },
          "categoryImage": {
            "type": "string",
            "nullable": true
          },
          "url": {
            "maxLength": 200,
            "minLength": 0,
            "pattern": "^[a-zA-Z0-9-_]+$",
            "type": "string"
          },
          "color": {
            "$ref": "#/components/schemas/CategoryColorsNullable"
          },
          "blogs": {
            "type": "array",
            "items": {
              "$ref": "#/components/schemas/Blog"
            },
            "nullable": true
          }
        },
        "additionalProperties": false
      },
      "CategoryColorsNullable": {
        "enum": [
          0,
          1,
          2,
          3,
          4,
          5,
          null
        ],
        "type": "integer",
        "format": "int32",
        "nullable": true
      },
      "Comment": {
        "type": "object",
        "properties": {
          "commentId": {
            "type": "integer",
            "format": "int32"
          },
          "text": {
            "type": "string",
            "nullable": true
          },
          "createdDate": {
            "type": "string",
            "format": "date-time",
            "nullable": true
          },
          "updatedDate": {
            "type": "string",
            "format": "date-time",
            "nullable": true
          },
          "blogId": {
            "type": "integer",
            "format": "int32"
          },
          "blog": {
            "$ref": "#/components/schemas/Blog"
          },
          "userId": {
            "type": "integer",
            "format": "int32"
          },
          "user": {
            "$ref": "#/components/schemas/User"
          }
        },
        "additionalProperties": false
      },
      "User": {
        "required": [
          "email",
          "firstName",
          "lastName",
          "password",
          "userName"
        ],
        "type": "object",
        "properties": {
          "userId": {
            "type": "integer",
            "format": "int32"
          },
          "userName": {
            "maxLength": 50,
            "minLength": 3,
            "type": "string"
          },
          "firstName": {
            "maxLength": 50,
            "minLength": 2,
            "type": "string"
          },
          "lastName": {
            "maxLength": 50,
            "minLength": 2,
            "type": "string"
          },
          "email": {
            "maxLength": 100,
            "minLength": 0,
            "type": "string",
            "format": "email"
          },
          "password": {
            "maxLength": 100,
            "minLength": 5,
            "type": "string",
            "format": "password"
          },
          "image": {
            "type": "string",
            "nullable": true
          },
          "registerDate": {
            "type": "string",
            "format": "date-time"
          },
          "blogs": {
            "type": "array",
            "items": {
              "$ref": "#/components/schemas/Blog"
            },
            "nullable": true
          },
          "comments": {
            "type": "array",
            "items": {
              "$ref": "#/components/schemas/Comment"
            },
            "nullable": true
          }
        },
        "additionalProperties": false
      }
    }
  }
}